oracle/__init__.py
oracle/cli.py
oracle/eight_ball.py
oracle/fortune_cookie.py
oracle/petting_zoo.py
oracle/vibe_check.py
Random_Oracle-0.1.0.dist-info/LICENSE
Random_Oracle-0.1.0.dist-info/METADATA
Random_Oracle-0.1.0.dist-info/WHEEL
Random_Oracle-0.1.0.dist-info/entry_points.txt
Random_Oracle-0.1.0.dist-info/top_level.txt
Random_Oracle-0.1.0.dist-info/RECORD
