Metadata-Version: 2.1
Name: Random-Oracle
Version: 0.1.0
Summary: Built Oracle, a prophet that can do multiple things, including spit fortunes (fortune cookie), output a random decision (8ball), give a quick, random mood (vibe check), and output a random pet (petting zoo).
Author-email: Christopher Li <cl6591@nyu.edu>, Julie Chen <jc11048@nyu.edu>, Aneri Shah <aneri.shah@nyu.edu>, Maddy Li <maddyli@nyu.edu>
License: GNU GENERAL PUBLIC LICENSE
Project-URL: Homepage, https://github.com/software-students-fall2024/3-python-package-burger-flippers
Project-URL: Repository, https://github.com/software-students-fall2024/3-python-package-burger-flippers.git
Project-URL: Bug Tracker, https://github.com/software-students-fall2024/3-python-package-burger-flippers/issues
Keywords: oracle,fortune,8-ball,vibe check,petting zoo,python package
Classifier: Programming Language :: Python :: 3
Classifier: Intended Audience :: Education
Classifier: License :: OSI Approved :: GNU General Public License v3 (GPLv3)
Classifier: Operating System :: OS Independent
Requires-Python: >=3.7
License-File: LICENSE
Provides-Extra: dev
Requires-Dist: pytest; extra == "dev"
